{
  "$schema": "../node_modules/@tauri-apps/cli/config.schema.json",
  "productName": "Pokedex",
  "version": "0.1.0",
  "identifier": "pokedex.project",
  "build": {
    "frontendDist": "../dist",
    "beforeDevCommand": "pnpm run dev",
    "beforeBuildCommand": "pnpm run build"
  },
  "app": {
    "windows": [
      {
        "title": "Pokedex",
        "width": 800,
        "height": 600,
        "resizable": true,
        "fullscreen": false
      }
    ],
    "security": {
      "csp": null
    }
  },
  "bundle": {
    "active": true,
    "targets": ["msi", "nsis"],
    "icon": [
      "icons/32x32.png",
      "icons/128x128.png",
      "icons/128x128@2x.png",
      "icons/icon.icns",
      "icons/icon.ico"
    ],
    "windows": {
      "certificateThumbprint": null,
      "digestAlgorithm": "sha256",
      "timestampUrl": "http://timestamp.digicert.com",
      "webviewInstallMode": {
        "type": "skip"
      }
    }
  }
}
